[{"__symbolic":"module","version":3,"metadata":{"ChangeEvent":{"__symbolic":"interface"},"VirtualScrollComponent":{"__symbolic":"class","decorators":[{"__symbolic":"call","expression":{"__symbolic":"reference","module":"@angular/core","name":"Component"},"arguments":[{"selector":"virtual-scroll,[virtualScroll]","exportAs":"virtualScroll","template":"\n    <div class=\"total-padding\" #shim></div>\n    <div class=\"scrollable-content\" #content>\n      <ng-content></ng-content>\n    </div>\n  ","host":{"[style.overflow-y]":"parentScroll ? 'hidden' : 'auto'","$quoted$":["[style.overflow-y]"]},"styles":["\n    :host {\n      overflow: hidden;\n      position: relative;\n      display: block;\n      -webkit-overflow-scrolling: touch;\n    }\n\n    .scrollable-content {\n      top: 0;\n      left: 0;\n      width: 100%;\n      height: 100%;\n      position: absolute;\n    }\n\n    .total-padding {\n      width: 1px;\n      opacity: 0;\n    }\n  "]}]}],"members":{"items":[{"__symbolic":"property","decorators":[{"__symbolic":"call","expression":{"__symbolic":"reference","module":"@angular/core","name":"Input"}}]}],"scrollbarWidth":[{"__symbolic":"property","decorators":[{"__symbolic":"call","expression":{"__symbolic":"reference","module":"@angular/core","name":"Input"}}]}],"scrollbarHeight":[{"__symbolic":"property","decorators":[{"__symbolic":"call","expression":{"__symbolic":"reference","module":"@angular/core","name":"Input"}}]}],"childWidth":[{"__symbolic":"property","decorators":[{"__symbolic":"call","expression":{"__symbolic":"reference","module":"@angular/core","name":"Input"}}]}],"childHeight":[{"__symbolic":"property","decorators":[{"__symbolic":"call","expression":{"__symbolic":"reference","module":"@angular/core","name":"Input"}}]}],"bufferAmount":[{"__symbolic":"property","decorators":[{"__symbolic":"call","expression":{"__symbolic":"reference","module":"@angular/core","name":"Input"}}]}],"scrollAnimationTime":[{"__symbolic":"property","decorators":[{"__symbolic":"call","expression":{"__symbolic":"reference","module":"@angular/core","name":"Input"}}]}],"doNotCheckAngularZone":[{"__symbolic":"property","decorators":[{"__symbolic":"call","expression":{"__symbolic":"reference","module":"@angular/core","name":"Input"}}]}],"parentScroll":[{"__symbolic":"property","decorators":[{"__symbolic":"call","expression":{"__symbolic":"reference","module":"@angular/core","name":"Input"}}]}],"update":[{"__symbolic":"property","decorators":[{"__symbolic":"call","expression":{"__symbolic":"reference","module":"@angular/core","name":"Output"}}]}],"change":[{"__symbolic":"property","decorators":[{"__symbolic":"call","expression":{"__symbolic":"reference","module":"@angular/core","name":"Output"}}]}],"start":[{"__symbolic":"property","decorators":[{"__symbolic":"call","expression":{"__symbolic":"reference","module":"@angular/core","name":"Output"}}]}],"end":[{"__symbolic":"property","decorators":[{"__symbolic":"call","expression":{"__symbolic":"reference","module":"@angular/core","name":"Output"}}]}],"contentElementRef":[{"__symbolic":"property","decorators":[{"__symbolic":"call","expression":{"__symbolic":"reference","module":"@angular/core","name":"ViewChild"},"arguments":["content",{"read":{"__symbolic":"reference","module":"@angular/core","name":"ElementRef"}}]}]}],"shimElementRef":[{"__symbolic":"property","decorators":[{"__symbolic":"call","expression":{"__symbolic":"reference","module":"@angular/core","name":"ViewChild"},"arguments":["shim",{"read":{"__symbolic":"reference","module":"@angular/core","name":"ElementRef"}}]}]}],"containerElementRef":[{"__symbolic":"property","decorators":[{"__symbolic":"call","expression":{"__symbolic":"reference","module":"@angular/core","name":"ContentChild"},"arguments":["container",{"read":{"__symbolic":"reference","module":"@angular/core","name":"ElementRef"}}]}]}],"__ctor__":[{"__symbolic":"constructor","parameters":[{"__symbolic":"reference","module":"@angular/core","name":"ElementRef"},{"__symbolic":"reference","module":"@angular/core","name":"Renderer2"},{"__symbolic":"reference","module":"@angular/core","name":"NgZone"}]}],"ngOnInit":[{"__symbolic":"method"}],"ngOnDestroy":[{"__symbolic":"method"}],"ngOnChanges":[{"__symbolic":"method"}],"refresh":[{"__symbolic":"method"}],"scrollInto":[{"__symbolic":"method"}],"getElement":[{"__symbolic":"method"}],"addParentEventHandlers":[{"__symbolic":"method"}],"removeParentEventHandlers":[{"__symbolic":"method"}],"countItemsPerRow":[{"__symbolic":"method"}],"getElementsOffset":[{"__symbolic":"method"}],"calculateDimensions":[{"__symbolic":"method"}],"calculateItems":[{"__symbolic":"method"}]}},"VirtualScrollModule":{"__symbolic":"class","decorators":[{"__symbolic":"call","expression":{"__symbolic":"reference","module":"@angular/core","name":"NgModule"},"arguments":[{"exports":[{"__symbolic":"reference","name":"VirtualScrollComponent"}],"declarations":[{"__symbolic":"reference","name":"VirtualScrollComponent"}]}]}]}}},{"__symbolic":"module","version":1,"metadata":{"ChangeEvent":{"__symbolic":"interface"},"VirtualScrollComponent":{"__symbolic":"class","decorators":[{"__symbolic":"call","expression":{"__symbolic":"reference","module":"@angular/core","name":"Component"},"arguments":[{"selector":"virtual-scroll,[virtualScroll]","exportAs":"virtualScroll","template":"\n    <div class=\"total-padding\" #shim></div>\n    <div class=\"scrollable-content\" #content>\n      <ng-content></ng-content>\n    </div>\n  ","host":{"[style.overflow-y]":"parentScroll ? 'hidden' : 'auto'"},"styles":["\n    :host {\n      overflow: hidden;\n      position: relative;\n      display: block;\n      -webkit-overflow-scrolling: touch;\n    }\n\n    .scrollable-content {\n      top: 0;\n      left: 0;\n      width: 100%;\n      height: 100%;\n      position: absolute;\n    }\n\n    .total-padding {\n      width: 1px;\n      opacity: 0;\n    }\n  "]}]}],"members":{"items":[{"__symbolic":"property","decorators":[{"__symbolic":"call","expression":{"__symbolic":"reference","module":"@angular/core","name":"Input"}}]}],"scrollbarWidth":[{"__symbolic":"property","decorators":[{"__symbolic":"call","expression":{"__symbolic":"reference","module":"@angular/core","name":"Input"}}]}],"scrollbarHeight":[{"__symbolic":"property","decorators":[{"__symbolic":"call","expression":{"__symbolic":"reference","module":"@angular/core","name":"Input"}}]}],"childWidth":[{"__symbolic":"property","decorators":[{"__symbolic":"call","expression":{"__symbolic":"reference","module":"@angular/core","name":"Input"}}]}],"childHeight":[{"__symbolic":"property","decorators":[{"__symbolic":"call","expression":{"__symbolic":"reference","module":"@angular/core","name":"Input"}}]}],"bufferAmount":[{"__symbolic":"property","decorators":[{"__symbolic":"call","expression":{"__symbolic":"reference","module":"@angular/core","name":"Input"}}]}],"scrollAnimationTime":[{"__symbolic":"property","decorators":[{"__symbolic":"call","expression":{"__symbolic":"reference","module":"@angular/core","name":"Input"}}]}],"doNotCheckAngularZone":[{"__symbolic":"property","decorators":[{"__symbolic":"call","expression":{"__symbolic":"reference","module":"@angular/core","name":"Input"}}]}],"parentScroll":[{"__symbolic":"property","decorators":[{"__symbolic":"call","expression":{"__symbolic":"reference","module":"@angular/core","name":"Input"}}]}],"update":[{"__symbolic":"property","decorators":[{"__symbolic":"call","expression":{"__symbolic":"reference","module":"@angular/core","name":"Output"}}]}],"change":[{"__symbolic":"property","decorators":[{"__symbolic":"call","expression":{"__symbolic":"reference","module":"@angular/core","name":"Output"}}]}],"start":[{"__symbolic":"property","decorators":[{"__symbolic":"call","expression":{"__symbolic":"reference","module":"@angular/core","name":"Output"}}]}],"end":[{"__symbolic":"property","decorators":[{"__symbolic":"call","expression":{"__symbolic":"reference","module":"@angular/core","name":"Output"}}]}],"contentElementRef":[{"__symbolic":"property","decorators":[{"__symbolic":"call","expression":{"__symbolic":"reference","module":"@angular/core","name":"ViewChild"},"arguments":["content",{"read":{"__symbolic":"reference","module":"@angular/core","name":"ElementRef"}}]}]}],"shimElementRef":[{"__symbolic":"property","decorators":[{"__symbolic":"call","expression":{"__symbolic":"reference","module":"@angular/core","name":"ViewChild"},"arguments":["shim",{"read":{"__symbolic":"reference","module":"@angular/core","name":"ElementRef"}}]}]}],"containerElementRef":[{"__symbolic":"property","decorators":[{"__symbolic":"call","expression":{"__symbolic":"reference","module":"@angular/core","name":"ContentChild"},"arguments":["container",{"read":{"__symbolic":"reference","module":"@angular/core","name":"ElementRef"}}]}]}],"__ctor__":[{"__symbolic":"constructor","parameters":[{"__symbolic":"reference","module":"@angular/core","name":"ElementRef"},{"__symbolic":"reference","module":"@angular/core","name":"Renderer2"},{"__symbolic":"reference","module":"@angular/core","name":"NgZone"}]}],"ngOnInit":[{"__symbolic":"method"}],"ngOnDestroy":[{"__symbolic":"method"}],"ngOnChanges":[{"__symbolic":"method"}],"refresh":[{"__symbolic":"method"}],"scrollInto":[{"__symbolic":"method"}],"getElement":[{"__symbolic":"method"}],"addParentEventHandlers":[{"__symbolic":"method"}],"removeParentEventHandlers":[{"__symbolic":"method"}],"countItemsPerRow":[{"__symbolic":"method"}],"getElementsOffset":[{"__symbolic":"method"}],"calculateDimensions":[{"__symbolic":"method"}],"calculateItems":[{"__symbolic":"method"}]}},"VirtualScrollModule":{"__symbolic":"class","decorators":[{"__symbolic":"call","expression":{"__symbolic":"reference","module":"@angular/core","name":"NgModule"},"arguments":[{"exports":[{"__symbolic":"reference","name":"VirtualScrollComponent"}],"declarations":[{"__symbolic":"reference","name":"VirtualScrollComponent"}]}]}]}}}]